mmn/__init__.py
mmn/indexer_client.py
mmn/mmn_client.py
mmn/types.py
mmn/zk_client.py
mmn_sdk-0.1.0.dist-info/licenses/LICENSE
mmn_sdk-0.1.0.dist-info/METADATA
mmn_sdk-0.1.0.dist-info/WHEEL
mmn_sdk-0.1.0.dist-info/top_level.txt
mmn_sdk-0.1.0.dist-info/RECORD
