Metadata-Version: 2.4
Name: mmn-sdk
Version: 0.1.0
Summary: Add your description here
License-Expression: Apache-2.0
Project-URL: Homepage, https://github.com/phuvinh010701/mmn-sdk-python
Project-URL: Issues, https://github.com/phuvinh010701/mmn-sdk-python/issues
Requires-Python: >=3.13
License-File: LICENSE
Requires-Dist: aiohttp>=3.13.2
Requires-Dist: base58>=2.1.1
Requires-Dist: pycryptodome>=3.23.0
Requires-Dist: pydantic>=2.12.3
Requires-Dist: pynacl>=1.6.0
Dynamic: license-file
